taranis.py
taranis-0.2.0.dist-info/LICENSE
taranis-0.2.0.dist-info/METADATA
taranis-0.2.0.dist-info/WHEEL
taranis-0.2.0.dist-info/top_level.txt
taranis-0.2.0.dist-info/RECORD
