Metadata-Version: 2.1
Name: taranis
Version: 0.2.0
Summary: Python API wrapper for weather-api
Home-page: https://github.com/esadek/taranis
Author: Emil Sadek
Author-email: esadek@hotmail.com
License: UNKNOWN
Platform: UNKNOWN
Classifier: Programming Language :: Python :: 3
Classifier: License :: OSI Approved :: MIT License
Classifier: Operating System :: OS Independent
License-File: LICENSE
Requires-Dist: requests
